quantagrad/__init__.py
quantagrad/activations.py
quantagrad/activations_base_class.py
quantagrad/engine.py
quantagrad/logger.py
quantagrad/loss_functions.py
quantagrad/module.py
quantagrad/neural_net.py
quantagrad/operations.py
quantagrad/optimizers.py
quantagrad-0.1.0.dist-info/LICENSE
quantagrad-0.1.0.dist-info/METADATA
quantagrad-0.1.0.dist-info/WHEEL
quantagrad-0.1.0.dist-info/top_level.txt
quantagrad-0.1.0.dist-info/RECORD
