Metadata-Version: 2.1
Name: quantagrad
Version: 0.1.0
Summary: An autograd engine with a PyTorch-like neural network library on top.
Home-page: https://github.com/Tony-Ale/quantagrad
Author: Oluwaseun Ale-Alaba
Author-email: carmichael8821@gmail.com
Classifier: Programming Language :: Python :: 3
Classifier: License :: OSI Approved :: MIT License
Classifier: Operating System :: OS Independent
Requires-Python: >=3.6
License-File: LICENSE
Requires-Dist: numpy >=1.26.4
